tests/__init__.py
tests/api_test.py
tests/base_api_test.py
tests/bath_test.py
tests/control_test.py
tests/correlations_test.py
tests/dynamics_test.py
tests/exceptions_test.py
tests/file_formats_test.py
tests/helpers_test.py
tests/operators_test.py
tests/process_tensor_test.py
tests/pt_tempo_test.py
tests/system_test.py
tests/tempo_test.py
tests/util_test.py
tests/backends/__init__.py
tests/backends/backend_factory_test.py
tests/backends/base_backends_test.py
tests/backends/example_A_test.py
tests/backends/example_B_test.py
tests/backends/example_C_test.py
tests/backends/example_D_test.py
tests/backends/example_E_test.py
tests/backends/process_tensor_backends_test.py
tests/backends/tensor_network_node_array_test.py
time_evolving_mpo/__init__.py
time_evolving_mpo/base_api.py
time_evolving_mpo/bath.py
time_evolving_mpo/config.py
time_evolving_mpo/control.py
time_evolving_mpo/correlations.py
time_evolving_mpo/dynamics.py
time_evolving_mpo/exceptions.py
time_evolving_mpo/file_formats.py
time_evolving_mpo/helpers.py
time_evolving_mpo/operators.py
time_evolving_mpo/process_tensor.py
time_evolving_mpo/pt_tempo.py
time_evolving_mpo/system.py
time_evolving_mpo/tempo.py
time_evolving_mpo/util.py
time_evolving_mpo/version.py
time_evolving_mpo/backends/__init__.py
time_evolving_mpo/backends/backend_factory.py
time_evolving_mpo/backends/base_backends.py
time_evolving_mpo/backends/tensor_network/__init__.py
time_evolving_mpo/backends/tensor_network/node_array.py
time_evolving_mpo/backends/tensor_network/process_tensor_backend.py
time_evolving_mpo/backends/tensor_network/pt_tempo_backend.py
time_evolving_mpo/backends/tensor_network/tempo_backend.py
time_evolving_mpo/backends/tensor_network/util.py
time_evolving_mpo-0.1.2.dist-info/AUTHORS.md
time_evolving_mpo-0.1.2.dist-info/LICENSE
time_evolving_mpo-0.1.2.dist-info/METADATA
time_evolving_mpo-0.1.2.dist-info/WHEEL
time_evolving_mpo-0.1.2.dist-info/top_level.txt
time_evolving_mpo-0.1.2.dist-info/RECORD
