Metadata-Version: 2.1
Name: time-evolving-mpo
Version: 0.1.2
Summary: A python3 library to efficiently compute non-markovian open quantum systems.
Home-page: http://github.com/tempoCollaboration/TimeEvolvingMPO
Author: TEMPO Collaboration
Author-email: tempo.collaboration@gmail.com
License: Apache 2.0
Keywords: physics,computational-physics,quantum-physics,quantum-information,open-quantum-systems
Platform: UNKNOWN
Classifier: Programming Language :: Python :: 3.6
Classifier: License :: OSI Approved :: Apache Software License
Classifier: Operating System :: OS Independent
Requires-Python: >=3.6.0
Requires-Dist: numpy (>=1.18.0)
Requires-Dist: scipy (>=1.4.0)
Requires-Dist: tensornetwork (==0.4.3)
Requires-Dist: matplotlib (>=3.0.0)
